{"type":"FeatureCollection","features":[{"type":"Feature","properties":{"marker-color":"#7e7e7e","marker-size":"medium","marker-symbol":"","name":"My Best Friend"},"geometry":{"type":"Point","coordinates":[-87.66538918018341,42.01035443994431]}},{"type":"Feature","properties":{},"geometry":{"type":"Point","coordinates":[-87.66326755285263,42.0103863270623]}},{"type":"Feature","properties":{},"geometry":{"type":"Point","coordinates":[-87.66247093677521,42.01040227061527]}},{"type":"Feature","properties":{},"geometry":{"type":"Point","coordinates":[-87.66285449266434,42.01161596185559]}},{"type":"Feature","properties":{},"geometry":{"type":"Point","coordinates":[-87.6634418964386,42.012825644202145]}},{"type":"Feature","properties":{},"geometry":{"type":"Point","coordinates":[-87.66404539346695,42.01394363329442]}},{"type":"Feature","properties":{"marker-color":"#7e7e7e","marker-size":"medium","marker-symbol":"","name":"My House"},"geometry":{"type":"Point","coordinates":[-87.66301006078719,42.013959575955745]}}]}